testcpu.v
module PC #(parameter WIDTH=32)(
//author:XJTU mry
    input clk,reset,
    input [WIDTH-1:0] d,
    output reg[WIDTH-1:0] q
    );
    always @(posedge clk,posedge reset)
    if(reset)q<=0;
    else q<=d;
endmodule

module PC_adder(
    adr,n_adr
    );
    //author:XJTU mry
    input [31:0] adr;
    output [31:0] n_adr;
    assign n_adr = adr + 32'd4;
endmodule

module codeRAM(
    address,data
    );
    //author:XJTU mry
        parameter DataWidth=32;
    parameter AddrWidth=32;
    parameter DataDepth=32;
    
    input [AddrWidth-1:0] address;

    output [DataWidth-1:0] data;
    //reg[4:0] n;
    //reg [DataWidth-1:0] data_out;
    reg [DataWidth-1:0] men [0:DataDepth-1];
    assign data=men[address[6:2]];
  
    initial 
    begin
        men[0]=32'h20020005;
        men[1]=32'h2003000c;
        men[2]=32'h2067fff7;
        men[3]=32'h00e22025;
        men[4]=32'h00642824;
        men[5]=32'h00a42820;
        men[6]=32'h10a7000a;
        men[7]=32'h0064202a;
        men[8]=32'h10800001;
        men[9]=32'h20050000;
        men[10]=32'h00e2202a;
        men[11]=32'h10800001;
        men[12]=32'h20050000;
        men[13]=32'h00e2202a;
        men[14]=32'h00853820;
        men[15]=32'h00e23822;
        men[16]=32'hac670044;
        men[17]=32'h8c020050;
        men[18]=32'h08000011;
        men[19]=32'h20020001;
        men[20]=32'hac020054;
    end
endmodule

module mainDec(
//author:XJTU mry
    input [5:0] op,
    output mentoreg,menwrite,
    output branch,alusrc,
    output regdst,regwrite,
    output jump,
    output [1:0] aluop
    );
    reg [8:0] controls;
    assign{regwrite,regdst,alusrc,branch,menwrite,mentoreg,jump,aluop}=controls;
    always @(*)
        case(op)
            6'b000000:controls<=9'b110000010; //R
            6'b100011:controls<=9'b101001000;//lw
            6'b101011:controls<=9'b001010000; //sw
            6'b000100:controls<=9'b000100001; //beq
            6'b001000:controls<=9'b101000000; //addi
            6'b000010:controls<=9'b000000100; //jmp
            default:controls<=9'bxxxxxxxxx;
        endcase
endmodule

module MUX6(
//author:XJTU mry
    A,B,Src,S
    );
    input [4:0] A,B;
    input Src;
    output [4:0] S;
    assign S = (Src==0) ? A:B;
endmodule

module RegisterUnit(
//author:XJTU mry
    clk,we,ra1,ra2,wa3,wd,rd1,rd2
    );
    parameter DataWidth=32;
    parameter AddrWidth=5;
    parameter DataDepth=1<<AddrWidth;
        input clk;
        input we;
        input [AddrWidth-1:0] ra1,ra2,wa3;
        input [DataWidth-1:0] wd;
        output [DataWidth-1:0] rd1,rd2;
        reg [DataWidth-1:0] rf [DataDepth-1:0];
        assign rd1=rf[ra1];
        assign rd2=rf[ra2];
        always @ (posedge clk)
        begin :MEM_WRITE
            if(we)begin
                rf[wa3]=wd;
            end
        end
        initial 
            begin
                rf[0]=32'h0;
                rf[1]=32'h0;
                rf[2]=32'h0;
                rf[3]=32'h0;
                rf[4]=32'h0;
                rf[5]=32'h0;
                rf[6]=32'h0;
                rf[7]=32'h0;
                rf[8]=32'h0;
                rf[9]=32'h0;
                rf[10]=32'h0;
                rf[11]=32'h0;
                rf[12]=32'h0;
                rf[13]=32'h0;
                rf[14]=32'h0;
                rf[15]=32'h0;
                rf[16]=32'h0;
            end

endmodule

module Extend16to32(
//author:XJTU mry
    order,addr
    );
    input [15:0] order;
    output reg [31:0] addr;
     
    always @(order)//complement
    begin
       if(order[15]==1) addr[31:16]=16'b1111111111111111;
    else addr[31:16]=16'b0000000000000000;
        addr[15:0]=order[15:0];
    end
endmodule

module MUX32(
//author:XJTU mry
A,B,Src,S
    );
    input [31:0] A,B;
    input Src;
    output [31:0] S;
    assign S = (Src==0) ? A:B;
endmodule

module aluDec(
//author:XJTU mry
    input [5:0]funct,
    input [1:0]aluop,
    output reg [3:0] alucontrol
    );
    always @(*)
        case(aluop)
            2'b00:alucontrol<=3'b0010;
            2'b01:alucontrol<=3'b0011;
        default:case(funct)
                    6'b100000:alucontrol<=4'b0010;//ADD
                    6'b100001:alucontrol<=4'b0000;//ADDU
                    6'b100010:alucontrol<=4'b0011;//SUB
                    6'b100011:alucontrol<=4'b0001;//SUBU
                    6'b100100:alucontrol<=4'b0100;//AND
                    6'b100101:alucontrol<=4'b0101;//OR
                    6'b100110:alucontrol<=4'b0110;//XOR
                    6'b100111:alucontrol<=4'b0111;//NOR
                    6'b101010:alucontrol<=4'b1011;//SLT
                    6'b101011:alucontrol<=4'b1010;//SLTU
                    default:alucontrol<=4'bxxxx;
                endcase
         endcase
endmodule

module alu(
//author:XJTU mry
        input [31:0] a,        //OP1
        input [31:0] b,        //OP2
        input [3:0] aluc,    //controller
        output [31:0] r,    //result
        output zero,
        output carry,
        output negative,
        output overflow);
        
    parameter Addu    =    4'b0000;    //r=a+b unsigned
    parameter Add    =    4'b0010;    //r=a+b signed
    parameter Subu    =    4'b0001;    //r=a-b unsigned
    parameter Sub    =    4'b0011;    //r=a-b signed
    parameter And    =    4'b0100;    //r=a&b
    parameter Or    =    4'b0101;    //r=a|b
    parameter Xor    =    4'b0110;    //r=a^b
    parameter Nor    =    4'b0111;    //r=~(a|b)
    //parameter Lui1    =    4'b1000;    //r={b[15:0],16'b0}
    //parameter Lui2    =    4'b1001;    //r={b[15:0],16'b0}
    parameter Slt    =    4'b1011;    //r=(a-b<0)?1:0 signed
    parameter Sltu    =    4'b1010;    //r=(a-b<0)?1:0 unsigned
    parameter Sra    =    4'b1100;    //r=b>>>a 
    parameter Sll    =    4'b1110;    //r=b<<a
    parameter Srl    =    4'b1101;    //r=b>>a
    
    parameter bits=31;
    parameter ENABLE=1,DISABLE=0;
    
    reg [32:0] result;
    wire signed [31:0] sa=a,sb=b;
    
    always@(*)begin
        case(aluc)
            Addu: begin
                result=a+b;
            end
            Subu: begin
                result=a-b;
            end
            Add: begin
                result=sa+sb;
            end
            Sub: begin
                result=sa-sb;
            end
            Sra: begin
                if(a==0) {result[31:0],result[32]}={b,1'b0};
                else {result[31:0],result[32]}=sb>>>(a-1);
            end
            Srl: begin
                if(a==0) {result[31:0],result[32]}={b,1'b0};
                else {result[31:0],result[32]}=b>>(a-1);
            end
            Sll: begin
                result=b<<a;
            end
            And: begin
                result=a&b;
            end
            Or: begin
                result=a|b;
            end
            Xor: begin
                result=a^b;
            end
            Nor: begin
                result=~(a|b);
            end
            Sltu: begin
                result=a<b?1:0;
            end
            Slt: begin
                result=sa<sb?1:0;
            end
            //Lui1,Lui2: result = {b[15:0], 16'b0};
            default:
                result=a+b;
        endcase
    end
    
    assign r=result[31:0];
    assign carry = result[32]; 
    assign zero=(r==32'b0)?1:0;
    assign negative=result[31];
    assign overflow=result[32];
endmodule

module RAM(
//author:XJTU mry
clk,address,data_in,data,we
    );
    parameter DataWidth=32;
    parameter AddrWidth=32;
    parameter DataDepth=32;
    input clk;
    input [AddrWidth-1:0] address;

    input we;
    input [DataWidth-1:0] data_in;
    output [DataWidth-1:0] data;
    
    reg [DataWidth-1:0] data_out;
    reg [DataWidth-1:0] men [0:DataDepth-1];
    assign data=(!we) ? data_out:8'bz;
    always @ (posedge clk)
    begin :MEM_WRITE
        if(we)begin
            men[address[6:2]]=data_in;
        end
    end
    
    always @ (posedge clk)
    begin :MEM_READ
        if(!we)begin
            data_out=men[address[6:2]];//?
        end
    end
endmodule

module Left2(data,odata);
//author:XJTU mry
 input [31:0] data;
 output reg [31:0] odata;

 always @(data)
 begin
    odata[31:2]<=data[29:0];
  odata[1:0]<=2'b00;
 end
endmodule

module ALU_Add_32(addr1,addr2,out_addr);
 input [31:0] addr1,addr2;
 output [31:0] out_addr;
 assign out_addr = addr1+addr2;
endmodule

module myand(
//author:XJTU mry
R,A,B
    );
    input A,B;
    output  R;
    assign R=A&B;
endmodule

module Left2_26(data,data1,odata);
//author:XJTU mry
 input [25:0] data;
 input [3:0] data1;
 output reg [31:0] odata;
 
 always @(data,data1)
 begin
    odata[27:2]<=data[25:0];
  odata[1:0]<=2'b00;
  odata[31:28]<=data1[3:0];
 end
endmodule

module CPU(
clk,rst,out_ALU,Read_Data1,Read_Data2,Address_in_PC,Address_out_PC,Address_Add_PC,Order,Read_Data_Mem,Order_Left,zero
    );
     input clk;
     input rst;
     //output [6:0] data1,data2,data3,data4;
     output [31:0]out_ALU;
     output [31:0] Read_Data1,Read_Data2,Address_in_PC,Address_out_PC,Address_Add_PC,Order,Read_Data_Mem,Order_Left;
     output zero;
     wire [31:0] Read_Data1;
     wire [31:0] Read_Data2;
     wire [31:0] Address_in_PC,Address_out_PC;//用于PC的输入和输出
     wire [31:0] Address_Add_PC;//用于程序计数器正常指令进行加4的输出
     wire [31:0] Order;//用于指令存储器的指令输出
     wire RegDst,Jump,Branch,MemtoReg,ALUSrc,RegWrite,MemWrite;//用于对控制信号的连线
     wire [1:0] ALUop;//控制信号ALUop的连线
     wire [4:0] Write_register;//寄存器堆中写入寄存器所在的位号的连线
     wire [31:0] Write_Data;//Read_Data1,Read_Data2;//寄存器堆中的连线
     wire [31:0] sign,out_sign,ALU1,out_ALU;
     wire [31:0] ALU_Add_32_out,Branch_or_normal;
     wire [3:0] ALU_ctr;
     wire [31:0] Read_Data_Mem;
     wire [31:0] Order_Left;
     wire zero,Mux32_EN;
     wire carry,negative,overflow;
     
     //PC(CLK,Address_in_PC,Address_out_PC,rst);
     PC pc(.clk(clk),.reset(rst),.d(Address_in_PC),.q(Address_out_PC));
      //Add_PC(Address_out_PC,Address_Add_PC);
      PC_adder pc_adder(.adr(Address_out_PC),.n_adr(Address_Add_PC));
      //Order_Mem(Address_out_PC,Order);
      codeRAM coderam(.address(Address_out_PC),.data(Order));
      //Control_Unit(Order[31:26],RegDst,Jump,Branch,MemRead,MemtoReg,ALUop,MemWrite,ALUSrc,RegWrite);
      mainDec maindec(.op(Order[31:26]),.mentoreg(MemtoReg),.menwrite(MemWrite),.branch(Branch),.alusrc(ALUSrc),.regdst(RegDst),.regwrite(RegWrite),.jump(Jump),.aluop(ALUop));
      //Mux_6(Order[20:16],Order[15:11],RegDst,Write_register);
      MUX6 mux6(.A(Order[20:16]),.B(Order[15:11]),.Src(RegDst),.S(Write_register));
      //Registers(Order[25:21],Order[20:16],Write_register,Write_Data,Read_Data1,Read_Data2,RegWrite,CLK);
      RegisterUnit ru(.clk(clk),.we(RegWrite),.ra1(Order[25:21]),.ra2(Order[20:16]),.wa3(Write_register),.wd(Write_Data),.rd1(Read_Data1),.rd2(Read_Data2));
      //sign_ep(Order[15:0],sign);
      Extend16to32 extend16to32(.order(Order[15:0]),.addr(sign));
      //Mux_32(Read_Data2,sign,ALUSrc,ALU1);
      MUX32 mux32_1(.A(Read_Data2),.B(sign),.Src(ALUSrc),.S(ALU1));
      //ALU_Control(ALUop,Order[5:0],ALU_ctr);
      aluDec aludec(.funct(Order[5:0]),.aluop(ALUop),.alucontrol(ALU_ctr));
      //ALU(ALU_ctr,Read_Data1,ALU1,zero,out_ALU);
      alu ALU(.a(Read_Data1),.b(ALU1),.aluc(ALU_ctr),.r(out_ALU),.zero(zero),.carry(carry),.negative(negative),.overflow(overflow));
      //Data_Mem(out_ALU,Read_Data2,Read_Data_Mem,CLK,MemWrite,MemRead);
      RAM ram(.clk(clk),.address(out_ALU),.data_in(Read_Data2),.data(Read_Data_Mem),.we(MemWrite));
      //Mux_32(out_ALU,Read_Data_Mem,MemtoReg,Write_Data);
      MUX32 MUX32_2(.A(out_ALU),.B(Read_Data_Mem),.Src(MemtoReg),.S(Write_Data));
      Left2 left2(.data(sign),.odata(out_sign));
      ALU_Add_32 aluadd32(.addr1(Address_Add_PC),.addr2(out_sign),.out_addr(ALU_Add_32_out));
      myand myand_(.R(Mux32_EN),.A(Branch),.B(zero));
      //Mux_32(Address_Add_PC,ALU_Add_32_out,Mux32_EN,Branch_or_normal);
      MUX32 mux32_3(.A(Address_Add_PC),.B(ALU_Add_32_out),.Src(Mux32_EN),.S(Branch_or_normal));
      Left2_26 left2_26(.data(Order[25:0]),.data1(Address_Add_PC[31:28]),.odata(Order_Left));
      //Mux_32(Branch_or_normal,Order_Left,Jump,Address_in_PC);
      MUX32 mux32_4(.A(Branch_or_normal),.B(Order_Left),.Src(Jump),.S(Address_in_PC));
endmodule

module sim_cpu(
//author:XJTU mry
    );
    reg  clk;
    reg rst;
         //output [6:0] data1,data2,data3,data4;
    wire [31:0]out_ALU;
    wire [31:0] Read_Data1,Read_Data2,Address_in_PC,Address_out_PC,Address_Add_PC,Order,Read_Data_Mem,Order_Left;
    wire zero;
    CPU cpu(
    .clk(clk),
    .rst(rst),
    .out_ALU(out_ALU),
    .Read_Data1(Read_Data1),
    .Read_Data2(Read_Data2),
    .Address_in_PC(Address_in_PC),
    .Address_out_PC(Address_out_PC),
    .Address_Add_PC(Address_Add_PC),
    .Order(Order),
    .Read_Data_Mem(Read_Data_Mem),
    .Order_Left(Order_Left),
    .zero(zero)
    );
    initial begin 
    $dumpfile("simcpu.vcd");
    $dumpvars;
    end
    always begin
        #10 clk=~clk;
    end
    initial begin
            clk=0;
            rst=0;
            #10;
            //clk=0;
            rst=1;
            #10;
            //clk=0;
            rst=0;
    end
    always begin
        #10 if($time>=1000)
        $finish;
    end
endmodule

simcpu.vcd
$date
	Sun Jan 29 08:47:01 2023
$end
$version
	Icarus Verilog
$end
$timescale
	1s
$end
$scope module sim_cpu $end
$var wire 1 ! zero $end
$var wire 32 " out_ALU [31:0] $end
$var wire 32 # Read_Data_Mem [31:0] $end
$var wire 32 $ Read_Data2 [31:0] $end
$var wire 32 % Read_Data1 [31:0] $end
$var wire 32 & Order_Left [31:0] $end
$var wire 32 ' Order [31:0] $end
$var wire 32 ( Address_out_PC [31:0] $end
$var wire 32 ) Address_in_PC [31:0] $end
$var wire 32 * Address_Add_PC [31:0] $end
$var reg 1 + clk $end
$var reg 1 , rst $end
$scope module cpu $end
$var wire 1 + clk $end
$var wire 1 , rst $end
$var wire 1 ! zero $end
$var wire 32 - sign [31:0] $end
$var wire 1 . overflow $end
$var wire 32 / out_sign [31:0] $end
$var wire 32 0 out_ALU [31:0] $end
$var wire 1 1 negative $end
$var wire 1 2 carry $end
$var wire 5 3 Write_register [4:0] $end
$var wire 32 4 Write_Data [31:0] $end
$var wire 1 5 RegWrite $end
$var wire 1 6 RegDst $end
$var wire 32 7 Read_Data_Mem [31:0] $end
$var wire 32 8 Read_Data2 [31:0] $end
$var wire 32 9 Read_Data1 [31:0] $end
$var wire 32 : Order_Left [31:0] $end
$var wire 32 ; Order [31:0] $end
$var wire 1 < Mux32_EN $end
$var wire 1 = MemtoReg $end
$var wire 1 > MemWrite $end
$var wire 1 ? Jump $end
$var wire 32 @ Branch_or_normal [31:0] $end
$var wire 1 A Branch $end
$var wire 32 B Address_out_PC [31:0] $end
$var wire 32 C Address_in_PC [31:0] $end
$var wire 32 D Address_Add_PC [31:0] $end
$var wire 2 E ALUop [1:0] $end
$var wire 4 F ALU_ctr [3:0] $end
$var wire 32 G ALU_Add_32_out [31:0] $end
$var wire 1 H ALUSrc $end
$var wire 32 I ALU1 [31:0] $end
$scope module ALU $end
$var wire 32 J sa [31:0] $end
$var wire 32 K sb [31:0] $end
$var wire 1 ! zero $end
$var wire 32 L r [31:0] $end
$var wire 1 . overflow $end
$var wire 1 1 negative $end
$var wire 1 2 carry $end
$var wire 32 M b [31:0] $end
$var wire 4 N aluc [3:0] $end
$var wire 32 O a [31:0] $end
$var reg 33 P result [32:0] $end
$upscope $end
$scope module MUX32_2 $end
$var wire 32 Q A [31:0] $end
$var wire 1 = Src $end
$var wire 32 R S [31:0] $end
$var wire 32 S B [31:0] $end
$upscope $end
$scope module aluadd32 $end
$var wire 32 T out_addr [31:0] $end
$var wire 32 U addr2 [31:0] $end
$var wire 32 V addr1 [31:0] $end
$upscope $end
$scope module aludec $end
$var wire 6 W funct [5:0] $end
$var wire 2 X aluop [1:0] $end
$var reg 4 Y alucontrol [3:0] $end
$upscope $end
$scope module coderam $end
$var wire 32 Z data [31:0] $end
$var wire 32 [ address [31:0] $end
$upscope $end
$scope module extend16to32 $end
$var wire 16 \ order [15:0] $end
$var reg 32 ] addr [31:0] $end
$upscope $end
$scope module left2 $end
$var wire 32 ^ data [31:0] $end
$var reg 32 _ odata [31:0] $end
$upscope $end
$scope module left2_26 $end
$var wire 26 ` data [25:0] $end
$var wire 4 a data1 [3:0] $end
$var reg 32 b odata [31:0] $end
$upscope $end
$scope module maindec $end
$var wire 6 c op [5:0] $end
$var wire 1 5 regwrite $end
$var wire 1 6 regdst $end
$var wire 1 > menwrite $end
$var wire 1 = mentoreg $end
$var wire 1 ? jump $end
$var wire 1 A branch $end
$var wire 1 H alusrc $end
$var wire 2 d aluop [1:0] $end
$var reg 9 e controls [8:0] $end
$upscope $end
$scope module mux32_1 $end
$var wire 32 f B [31:0] $end
$var wire 1 H Src $end
$var wire 32 g S [31:0] $end
$var wire 32 h A [31:0] $end
$upscope $end
$scope module mux32_3 $end
$var wire 32 i B [31:0] $end
$var wire 1 < Src $end
$var wire 32 j S [31:0] $end
$var wire 32 k A [31:0] $end
$upscope $end
$scope module mux32_4 $end
$var wire 32 l A [31:0] $end
$var wire 32 m B [31:0] $end
$var wire 1 ? Src $end
$var wire 32 n S [31:0] $end
$upscope $end
$scope module mux6 $end
$var wire 5 o A [4:0] $end
$var wire 5 p B [4:0] $end
$var wire 1 6 Src $end
$var wire 5 q S [4:0] $end
$upscope $end
$scope module myand_ $end
$var wire 1 A A $end
$var wire 1 ! B $end
$var wire 1 < R $end
$upscope $end
$scope module pc $end
$var wire 1 + clk $end
$var wire 32 r d [31:0] $end
$var wire 1 , reset $end
$var reg 32 s q [31:0] $end
$upscope $end
$scope module pc_adder $end
$var wire 32 t adr [31:0] $end
$var wire 32 u n_adr [31:0] $end
$upscope $end
$scope module ram $end
$var wire 32 v address [31:0] $end
$var wire 1 + clk $end
$var wire 1 > we $end
$var wire 32 w data_in [31:0] $end
$var wire 32 x data [31:0] $end
$var reg 32 y data_out [31:0] $end
$scope begin MEM_READ $end
$upscope $end
$scope begin MEM_WRITE $end
$upscope $end
$upscope $end
$scope module ru $end
$var wire 1 + clk $end
$var wire 5 z ra1 [4:0] $end
$var wire 5 { ra2 [4:0] $end
$var wire 32 | rd1 [31:0] $end
$var wire 32 } rd2 [31:0] $end
$var wire 5 ~ wa3 [4:0] $end
$var wire 32 !" wd [31:0] $end
$var wire 1 5 we $end
$scope begin MEM_WRITE $end
$upscope $end
$upscope $end
$upscope $end
$upscope $end
$enddefinitions $end
#0
$dumpvars
bx !"
bx ~
bx }
bx |
bx {
bx z
bx y
bx x
bx w
bx v
bx u
bx t
bx s
bx r
bx q
bx p
bx o
bx n
bx m
bx l
bx k
bx j
bx i
bx h
bx g
bx f
bx e
bx d
bx c
bx b
bx a
bx `
bx _
bx ^
bx ]
bx \
bx [
bx Z
bx Y
bx X
bx W
bx V
bx U
bx T
bx S
bx R
bx Q
bx P
bx O
bx N
bx M
bx L
bx K
bx J
bx I
xH
bx G
bx F
bx E
bx D
bx C
bx B
xA
bx @
x?
x>
x=
x<
bx ;
bx :
bx 9
bx 8
bx 7
x6
x5
bx 4
bx 3
x2
x1
bx 0
bx /
x.
bx -
0,
0+
bx *
bx )
bx (
bx '
bx &
bx %
bx $
bx #
bx "
x!
$end
#10
b10 F
b10 N
b10 Y
0!
b101 4
b101 R
b101 !"
b101 "
b101 0
b101 L
b101 Q
b101 v
02
01
0.
b101 P
0<
b100 )
b100 C
b100 n
b100 r
b100 @
b100 j
b100 l
15
06
1H
0A
0>
0=
0?
b0 E
b0 X
b0 d
b11000 G
b11000 T
b11000 i
b10100 /
b10100 U
b10100 _
b101000000 e
b10000000000000010100 &
b10000000000000010100 :
b10000000000000010100 b
b10000000000000010100 m
b101 K
b101 I
b101 M
b101 g
b101 -
b101 ]
b101 ^
b101 f
b10 3
b10 q
b10 ~
b100000000000000101 `
b101 W
b101 \
b0 $
b0 8
b0 h
b0 w
b0 }
b10 {
b0 J
b0 %
b0 9
b0 O
b0 |
b0 z
b0 p
b10 o
b1000 c
b0 a
b100000000000100000000000000101 '
b100000000000100000000000000101 ;
b100000000000100000000000000101 Z
b100 *
b100 D
b100 V
b100 k
b100 u
b0 (
b0 B
b0 [
b0 s
b0 t
1,
1+
#20
0,
0+
#30
b110000 /
b110000 U
b110000 _
b11000000000000110000 &
b11000000000000110000 :
b11000000000000110000 b
b11000000000000110000 m
b1100 4
b1100 R
b1100 !"
b1100 "
b1100 0
b1100 L
b1100 Q
b1100 v
b1100 P
b1100 K
b1100 I
b1100 M
b1100 g
b1100 -
b1100 ]
b1100 ^
b1100 f
b11 3
b11 q
b11 ~
b1000 )
b1000 C
b1000 n
b1000 r
b110000000000001100 `
b1100 W
b1100 \
b11 {
b11 o
b1000 @
b1000 j
b1000 l
b100000000000110000000000001100 '
b100000000000110000000000001100 ;
b100000000000110000000000001100 Z
b111000 G
b111000 T
b111000 i
b1000 *
b1000 D
b1000 V
b1000 k
b1000 u
b100 (
b100 B
b100 [
b100 s
b100 t
b0 $
b0 8
b0 h
b0 w
b0 }
1+
#40
0+
#50
b11111111111111111111111111011100 /
b11111111111111111111111111011100 U
b11111111111111111111111111011100 _
b1100111111111111111011100 &
b1100111111111111111011100 :
b1100111111111111111011100 b
b1100111111111111111011100 m
b11 4
b11 R
b11 !"
b11111111111111111111111111110111 K
b11111111111111111111111111110111 I
b11111111111111111111111111110111 M
b11111111111111111111111111110111 g
b11 "
b11 0
b11 L
b11 Q
b11 v
b11111111111111111111111111110111 -
b11111111111111111111111111110111 ]
b11111111111111111111111111110111 ^
b11111111111111111111111111110111 f
b11 P
b111 3
b111 q
b111 ~
b1100 )
b1100 C
b1100 n
b1100 r
b11001111111111111110111 `
b110111 W
b1111111111110111 \
b111 {
b1100 J
b1100 %
b1100 9
b1100 O
b1100 |
b11 z
b11111 p
b111 o
b1100 @
b1100 j
b1100 l
b100000011001111111111111110111 '
b100000011001111111111111110111 ;
b100000011001111111111111110111 Z
b11111111111111111111111111101000 G
b11111111111111111111111111101000 T
b11111111111111111111111111101000 i
b1100 *
b1100 D
b1100 V
b1100 k
b1100 u
b1000 (
b1000 B
b1000 [
b1000 s
b1000 t
b0 $
b0 8
b0 h
b0 w
b0 }
1+
#60
0+
#70
b101 F
b101 N
b101 Y
16
0H
b10 E
b10 X
b10 d
b1000000010010100 /
b1000000010010100 U
b1000000010010100 _
b11100010001000000010010100 &
b11100010001000000010010100 :
b11100010001000000010010100 b
b11100010001000000010010100 m
b110000010 e
b111 4
b111 R
b111 !"
b101 K
b101 I
b101 M
b101 g
b111 "
b111 0
b111 L
b111 Q
b111 v
02
01
0.
b10000000100101 -
b10000000100101 ]
b10000000100101 ^
b10000000100101 f
b111 P
b100 3
b100 q
b100 ~
b10000 )
b10000 C
b10000 n
b10000 r
b111000100010000000100101 `
b100101 W
b10000000100101 \
b10 {
b11 J
b11 %
b11 9
b11 O
b11 |
b111 z
b100 p
b10 o
b0 c
b10000 @
b10000 j
b10000 l
b111000100010000000100101 '
b111000100010000000100101 ;
b111000100010000000100101 Z
b1000000010100100 G
b1000000010100100 T
b1000000010100100 i
b10000 *
b10000 D
b10000 V
b10000 k
b10000 u
b1100 (
b1100 B
b1100 [
b1100 s
b1100 t
b101 $
b101 8
b101 h
b101 w
b101 }
1+
#80
0+
#90
b1010000010010000 /
b1010000010010000 U
b1010000010010000 _
b1100100001010000010010000 &
b1100100001010000010010000 :
b1100100001010000010010000 b
b1100100001010000010010000 m
b100 F
b100 N
b100 Y
b100 4
b100 R
b100 !"
b100 "
b100 0
b100 L
b100 Q
b100 v
b10100000100100 -
b10100000100100 ]
b10100000100100 ^
b10100000100100 f
b111 K
b111 I
b111 M
b111 g
b100 P
b101 3
b101 q
b101 ~
b10100 )
b10100 C
b10100 n
b10100 r
b11001000010100000100100 `
b100100 W
b10100000100100 \
b111 $
b111 8
b111 h
b111 w
b111 }
b100 {
b1100 J
b1100 %
b1100 9
b1100 O
b1100 |
b11 z
b101 p
b100 o
b10100 @
b10100 j
b10100 l
b11001000010100000100100 '
b11001000010100000100100 ;
b11001000010100000100100 Z
b1010000010100100 G
b1010000010100100 T
b1010000010100100 i
b10100 *
b10100 D
b10100 V
b10100 k
b10100 u
b10000 (
b10000 B
b10000 [
b10000 s
b10000 t
1+
#100
0+
#110
b1011 4
b1011 R
b1011 !"
b1011 "
b1011 0
b1011 L
b1011 Q
b1011 v
b1011 P
b1010000010000000 /
b1010000010000000 U
b1010000010000000 _
b10100100001010000010000000 &
b10100100001010000010000000 :
b10100100001010000010000000 b
b10100100001010000010000000 m
b10 F
b10 N
b10 Y
b10100000100000 -
b10100000100000 ]
b10100000100000 ^
b10100000100000 f
b11000 )
b11000 C
b11000 n
b11000 r
b101001000010100000100000 `
b100000 W
b10100000100000 \
b100 J
b100 %
b100 9
b100 O
b100 |
b101 z
b11000 @
b11000 j
b11000 l
b101001000010100000100000 '
b101001000010100000100000 ;
b101001000010100000100000 Z
b1010000010011000 G
b1010000010011000 T
b1010000010011000 i
b11000 *
b11000 D
b11000 V
b11000 k
b11000 u
b10100 (
b10100 B
b10100 [
b10100 s
b10100 t
1+
#120
0+
#130
05
06
1A
b1 E
b1 X
b1 d
b101000 /
b101000 U
b101000 _
b10100111000000000000101000 &
b10100111000000000000101000 :
b10100111000000000000101000 b
b10100111000000000000101000 m
b11 F
b11 N
b11 Y
b100001 e
b1010 -
b1010 ]
b1010 ^
b1010 f
b11 K
b11 I
b11 M
b11 g
b111 3
b111 q
b111 ~
b11100 )
b11100 C
b11100 n
b11100 r
b101001110000000000001010 `
b1010 W
b1010 \
b11 $
b11 8
b11 h
b11 w
b11 }
b111 {
b0 p
b111 o
b100 c
b11100 @
b11100 j
b11100 l
b10000101001110000000000001010 '
b10000101001110000000000001010 ;
b10000101001110000000000001010 Z
b1000100 G
b1000100 T
b1000100 i
b11100 *
b11100 D
b11100 V
b11100 k
b11100 u
b11000 (
b11000 B
b11000 [
b11000 s
b11000 t
b1000 4
b1000 R
b1000 !"
b1000 "
b1000 0
b1000 L
b1000 Q
b1000 v
b1000 P
b1011 J
b1011 %
b1011 9
b1011 O
b1011 |
1+
#140
0+
#150
1!
b1011 F
b1011 N
b1011 Y
15
16
0A
b10 E
b10 X
b10 d
b1000000010101000 /
b1000000010101000 U
b1000000010101000 _
b1100100001000000010101000 &
b1100100001000000010101000 :
b1100100001000000010101000 b
b1100100001000000010101000 m
b110000010 e
b0 4
b0 R
b0 !"
b0 "
b0 0
b0 L
b0 Q
b0 v
b10000000101010 -
b10000000101010 ]
b10000000101010 ^
b10000000101010 f
b111 K
b111 I
b111 M
b111 g
b0 P
b100 3
b100 q
b100 ~
b100000 )
b100000 C
b100000 n
b100000 r
b11001000010000000101010 `
b101010 W
b10000000101010 \
b111 $
b111 8
b111 h
b111 w
b111 }
b100 {
b1100 J
b1100 %
b1100 9
b1100 O
b1100 |
b11 z
b100 p
b100 o
b0 c
b100000 @
b100000 j
b100000 l
b11001000010000000101010 '
b11001000010000000101010 ;
b11001000010000000101010 Z
b1000000011001000 G
b1000000011001000 T
b1000000011001000 i
b100000 *
b100000 D
b100000 V
b100000 k
b100000 u
b11100 (
b11100 B
b11100 [
b11100 s
b11100 t
1+
#160
0+
#170
1<
05
06
1A
b1 E
b1 X
b1 d
b100 /
b100 U
b100 _
b10000000000000000000000100 &
b10000000000000000000000100 :
b10000000000000000000000100 b
b10000000000000000000000100 m
b11 F
b11 N
b11 Y
b100001 e
b1 -
b1 ]
b1 ^
b1 f
b0 3
b0 q
b0 ~
b101000 )
b101000 C
b101000 n
b101000 r
b100000000000000000000001 `
b1 W
b1 \
b0 {
b0 J
b0 %
b0 9
b0 O
b0 |
b100 z
b0 p
b0 o
b100 c
b101000 @
b101000 j
b101000 l
b10000100000000000000000000001 '
b10000100000000000000000000001 ;
b10000100000000000000000000001 Z
b101000 G
b101000 T
b101000 i
b100100 *
b100100 D
b100100 V
b100100 k
b100100 u
b100000 (
b100000 B
b100000 [
b100000 s
b100000 t
b0 K
b0 I
b0 M
b0 g
b0 $
b0 8
b0 h
b0 w
b0 }
1+
#180
0+
#190
b1011 F
b1011 N
b1011 Y
15
16
0A
b10 E
b10 X
b10 d
b1000000010101000 /
b1000000010101000 U
b1000000010101000 _
b11100010001000000010101000 &
b11100010001000000010101000 :
b11100010001000000010101000 b
b11100010001000000010101000 m
b110000010 e
0<
0!
02
01
0.
b1 4
b1 R
b1 !"
b1 "
b1 0
b1 L
b1 Q
b1 v
b10000000101010 -
b10000000101010 ]
b10000000101010 ^
b10000000101010 f
b101 K
b101 I
b101 M
b101 g
b1 P
b100 3
b100 q
b100 ~
b101100 )
b101100 C
b101100 n
b101100 r
b111000100010000000101010 `
b101010 W
b10000000101010 \
b101 $
b101 8
b101 h
b101 w
b101 }
b10 {
b11 J
b11 %
b11 9
b11 O
b11 |
b111 z
b100 p
b10 o
b0 c
b101100 @
b101100 j
b101100 l
b111000100010000000101010 '
b111000100010000000101010 ;
b111000100010000000101010 Z
b1000000011010100 G
b1000000011010100 T
b1000000011010100 i
b101100 *
b101100 D
b101100 V
b101100 k
b101100 u
b101000 (
b101000 B
b101000 [
b101000 s
b101000 t
1+
#200
0+
